[
  {
    "id": 301,
    "name": "Black Panda",
    "status": "ERROR",
    "exit_code": -1,
    "details": {
      "error": "Command '['python3', ' 'Black Panda']' timed out after 30 seconds"
    },
    "verified_at": "2025-12-20T16:40:38.865010"
  },
  {
    "id": 302,
    "name": "Clarity.fm",
    "status": "ERROR",
    "exit_code": -1,
    "details": {
      "error": "Command '['python3', ' 'Clarity.fm']' timed out after 30 seconds"
    },
    "verified_at": "2025-12-20T16:40:38.864648"
  },
  {
    "id": 303,
    "name": "NewtonX",
    "status": "ERROR",
    "exit_code": -1,
    "details": {
      "error": "Command '['python3', ' 'NewtonX']' timed out after 30 seconds"
    },
    "verified_at": "2025-12-20T16:40:38.863308"
  },
  {
    "id": 304,
    "name": "RealCISO",
    "status": "ERROR",
    "exit_code": -1,
    "details": {
      "error": "Command '['python3', ' 'RealCISO']' timed out after 30 seconds"
    },
    "verified_at": "2025-12-20T16:40:38.614170"
  },
  {
    "id": 305,
    "name": "Site.Sa",
    "status": "ERROR",
    "exit_code": -1,
    "details": {
      "error": "Command '['python3', ' 'Site.Sa']' timed out after 30 seconds"
    },
    "verified_at": "2025-12-20T16:41:09.233944"
  },
  {
    "id": 306,
    "name": "Glgroup",
    "status": "ERROR",
    "exit_code": -1,
    "details": {
      "error": "Command '['python3', ' 'Glgroup']' timed out after 30 seconds"
    },
    "verified_at": "2025-12-20T16:41:09.354921"
  },
  {
    "id": 307,
    "name": "Security-Gen",
    "status": "ERROR",
    "exit_code": -1,
    "details": {
      "error": "Command '['python3', ' 'Security-Gen']' timed out after 30 seconds"
    },
    "verified_at": "2025-12-20T16:41:09.342539"
  },
  {
    "id": 308,
    "name": "Emissary",
    "status": "ERROR",
    "exit_code": -1,
    "details": {
      "error": "Command '['python3', ' 'Emissary']' timed out after 30 seconds"
    },
    "verified_at": "2025-12-20T16:41:09.267985"
  }
]